hy2glsl/__init__.py
hy2glsl/library.hy
hy2glsl/translator.hy
hy2glsl-0.0.2.dist-info/COPYING
hy2glsl-0.0.2.dist-info/METADATA
hy2glsl-0.0.2.dist-info/WHEEL
hy2glsl-0.0.2.dist-info/top_level.txt
hy2glsl-0.0.2.dist-info/RECORD
