Metadata-Version: 2.1
Name: hy2glsl
Version: 0.0.2
Summary: UNKNOWN
Home-page: https://github.com/TristanCacqueray/hy2glsl
Author: Tristan de Cacqueray
Author-email: tristanC@wombatt.eu
License: GPL-3
Platform: any
Classifier: Development Status :: 3 - Alpha
Classifier: Intended Audience :: Developers
Classifier: License :: DFSG approved
Classifier: License :: OSI Approved :: GNU General Public License v3 or later (GPLv3+)
Classifier: Operating System :: OS Independent
Classifier: Programming Language :: Lisp
Classifier: Topic :: Software Development :: Libraries
Requires-Python: >=3.4
Requires-Dist: hy
